Workbook

Sheet Instructions
B2: NGFsystems — Profit & Loss Workbook
B3: Monthly business tracking · Foundation for taxes, decisions, and growth
B5: How to use this workbook
B6: This is your monthly P&L (profit and loss) tracking workbook. Use it to record income and expenses every month, see your gross and net margins, and have clean records for taxes and decision-making.
B8: • At the end of each month, open the "2026 P&L" sheet and fill in the BLUE cells under that month's column.
B9: • Income rows: enter how much you actually collected (not what was invoiced — only what cleared the bank).
B10: • Expense rows: enter what you actually paid for each category.
B11: • Black cells are formulas. Don't type into them — they calculate automatically.
B12: • YTD (column N) and Annual Projection (column O) update automatically as you fill in months.
B13: • When you add a new client, add a row to the "Clients" sheet. The Clients sheet is a reference for you — your MRR roster.
B14: • At year-end, the "Annual Summary" sheet is what your accountant wants. Save a copy as "NGFsystems-PL-2026-Final.xlsx" before starting 2027.
B16: Color key
B17: Blue text | C17: Your inputs. The cells you type into each month. Hardcoded values.
B18: Black text | C18: Formulas. Auto-calculated. Don't edit these.
B19: Green text | C19: Links to other sheets (e.g. totals pulled from the Clients sheet).
B20: Yellow background | C20: Cells flagged for attention or annual review.
B22: Monthly checklist — first week of each month
B23: • Open this workbook, go to the "2026 P&L" sheet, scroll to last month's column.
B24: • Fill in collected income for each category (recurring revenue collected, setup fees received, etc.).
B25: • Fill in expenses paid (Vercel, Claude Pro, domains, mileage, etc.).
B26: • Verify Net Income at the bottom of the column. Compare to last month — did it improve?
B27: • Update the Clients sheet if any new clients started or any churned.
B28: • Save the file. (Keep one master copy — don't make duplicates.)
B30: Quarterly tasks
B31: • Open Annual Summary sheet. Confirm the YTD numbers look right.
B32: • Review Gross Margin % and Net Margin %. Are they trending up or down?
B33: • Set aside estimated quarterly tax (typically ~25-30% of net profit). Move it to a separate savings account so it's not "available" cash.
B34: • If net profit is consistently positive, consider an accountant consultation.
... B41: • Compare YoY in the Annual Summary sheet — that's your growth story.

Sheet 2026 P&L
A1: NGFsystems — 2026 Profit & Loss
A3: Category | B3: Jan | C3: Feb | D3: Mar | E3: Apr | F3: May | G3: Jun | H3: Jul | I3: Aug | J3: Sep | K3: Oct | L3: Nov | M3: Dec | N3: YTD | O3: Annual Proj. | P3: Notes
A4: INCOME
A5: Recurring revenue — Starter ($100/mo clients) | F5: 100 | N5: =SUM(B5:M5) -> 100 | O5: =IF(COUNT(B5:M5)=0,0,N5*12/COUNT(B5:M5)) -> 1200 | P5: # active Starter clients × $100
A6: Recurring revenue — Professional ($350/mo clients) | N6: =SUM(B6:M6) -> 0 | O6: =IF(COUNT(B6:M6)=0,0,N6*12/COUNT(B6:M6)) -> 0 | P6: # active Professional clients × $350
A7: Recurring revenue — Premium ($600/mo clients) | N7: =SUM(B7:M7) -> 0 | O7: =IF(COUNT(B7:M7)=0,0,N7*12/COUNT(B7:M7)) -> 0 | P7: # active Premium clients × $600
A8: Setup fees collected | N8: =SUM(B8:M8) -> 0 | O8: =IF(COUNT(B8:M8)=0,0,N8*12/COUNT(B8:M8)) -> 0 | P8: One-time setup charged when new client onboards
A9: One-time builds collected | N9: =SUM(B9:M9) -> 0 | O9: =IF(COUNT(B9:M9)=0,0,N9*12/COUNT(B9:M9)) -> 0 | P9: Essential / Business / Enterprise full-ownership builds
A10: Maintenance billables (hourly work) | N10: =SUM(B10:M10) -> 0 | O10: =IF(COUNT(B10:M10)=0,0,N10*12/COUNT(B10:M10)) -> 0 | P10: Out-of-scope work billed at $80/hr
A11: Other income | N11: =SUM(B11:M11) -> 0 | O11: =IF(COUNT(B11:M11)=0,0,N11*12/COUNT(B11:M11)) -> 0 | P11: Anything that doesn't fit above. Note category.
A12: TOTAL INCOME | B12: =SUM(B5:B11) -> 0 | C12: =SUM(C5:C11) -> 0 | D12: =SUM(D5:D11) -> 0 | E12: =SUM(E5:E11) -> 0 | F12: =SUM(F5:F11) -> 100 | G12: =SUM(G5:G11) -> 0 | H12: =SUM(H5:H11) -> 0 | I12: =SUM(I5:I11) -> 0 | ... M12: =SUM(M5:M11) -> 0 | N12: =SUM(B12:M12) -> 100 | O12: =IF(COUNT(B11:M11)=0,0,N12*12/COUNT(B11:M11)) -> 0
A14: COST OF GOODS SOLD (direct per-client costs)
A15: Vercel — client site hosting | N15: =SUM(B15:M15) -> 0 | O15: =IF(COUNT(B15:M15)=0,0,N15*12/COUNT(B15:M15)) -> 0 | P15: Per-client Vercel project costs above free tier
A16: Domain renewals (allocated) | N16: =SUM(B16:M16) -> 0 | O16: =IF(COUNT(B16:M16)=0,0,N16*12/COUNT(B16:M16)) -> 0 | P16: Allocate client domain renewals here
A17: Email / Resend allocation | N17: =SUM(B17:M17) -> 0 | O17: =IF(COUNT(B17:M17)=0,0,N17*12/COUNT(B17:M17)) -> 0 | P17: Variable with email volume
A18: AI API for client support / edits | N18: =SUM(B18:M18) -> 0 | O18: =IF(COUNT(B18:M18)=0,0,N18*12/COUNT(B18:M18)) -> 0 | P18: Anthropic + OpenAI usage tied to client work
A19: TOTAL COGS | B19: =SUM(B15:B18) -> 0 | C19: =SUM(C15:C18) -> 0 | D19: =SUM(D15:D18) -> 0 | E19: =SUM(E15:E18) -> 0 | F19: =SUM(F15:F18) -> 0 | G19: =SUM(G15:G18) -> 0 | H19: =SUM(H15:H18) -> 0 | I19: =SUM(I15:I18) -> 0 | ... M19: =SUM(M15:M18) -> 0 | N19: =SUM(B19:M19) -> 0 | O19: =IF(COUNT(B18:M18)=0,0,N19*12/COUNT(B18:M18)) -> 0
A21: GROSS PROFIT | B21: =B12-B19 -> 0 | C21: =C12-C19 -> 0 | D21: =D12-D19 -> 0 | E21: =E12-E19 -> 0 | F21: =F12-F19 -> 100 | G21: =G12-G19 -> 0 | H21: =H12-H19 -> 0 | I21: =I12-I19 -> 0 | ... M21: =M12-M19 -> 0 | N21: =SUM(B21:M21) -> 100 | O21: =IF(COUNT(B20:M20)=0,0,N21*12/COUNT(B20:M20)) -> 0
A22: Gross margin | B22: =IFERROR(B21/B12,0) -> 0 | C22: =IFERROR(C21/C12,0) -> 0 | D22: =IFERROR(D21/D12,0) -> 0 | E22: =IFERROR(E21/E12,0) -> 0 | F22: =IFERROR(F21/F12,0) -> 1 | G22: =IFERROR(G21/G12,0) -> 0 | H22: =IFERROR(H21/H12,0) -> 0 | I22: =IFERROR(I21/I12,0) -> 0 | ... N22: =IFERROR(N21/N12,0) -> 1
A24: OPERATING EXPENSES
A25: Vercel Pro Plan (NGF main app) | B25: 20 | C25: 20 | D25: 20 | E25: 20 | F25: 20 | G25: 20 | H25: 20 | I25: 20 | J25: 20 | K25: 20 | L25: 20 | M25: 20 | N25: =SUM(B25:M25) -> 240 | O25: =IF(COUNT(B25:M25)=0,0,N25*12/COUNT(B25:M25)) -> 240 | P25: $20/mo flat. Verify each month — bill may include overages.
A26: Claude Pro / Anthropic API (dev usage) | B26: 100 | C26: 100 | D26: 100 | E26: 100 | F26: 100 | G26: 100 | H26: 100 | I26: 100 | J26: 100 | K26: 100 | L26: 100 | M26: 100 | N26: =SUM(B26:M26) -> 1200 | O26: =IF(COUNT(B26:M26)=0,0,N26*12/COUNT(B26:M26)) -> 1200 | P26: AI tooling cost for YOUR development work (not client-billed)
A27: NGF domains (.com / .org / .net) | B27: 3 | C27: 3 | D27: 3 | E27: 3 | F27: 3 | G27: 3 | H27: 3 | I27: 3 | J27: 3 | K27: 3 | L27: 3 | M27: 3 | N27: =SUM(B27:M27) -> 36 | O27: =IF(COUNT(B27:M27)=0,0,N27*12/COUNT(B27:M27)) -> 36 | P27: ~$34/year combined, allocated monthly
A28: Software subscriptions (Cursor, Figma, GitHub, etc.) | N28: =SUM(B28:M28) -> 0 | O28: =IF(COUNT(B28:M28)=0,0,N28*12/COUNT(B28:M28)) -> 0 | P28: Itemize in your records; total here
A29: Mileage / travel | N29: =SUM(B29:M29) -> 0 | O29: =IF(COUNT(B29:M29)=0,0,N29*12/COUNT(B29:M29)) -> 0 | P29: Track in a log. IRS mileage rate × miles driven for business.
A30: Marketing & advertising | N30: =SUM(B30:M30) -> 0 | O30: =IF(COUNT(B30:M30)=0,0,N30*12/COUNT(B30:M30)) -> 0 | P30: Ads, conference fees, business cards, etc.
A31: Professional services (accounting, legal) | N31: =SUM(B31:M31) -> 0 | O31: =IF(COUNT(B31:M31)=0,0,N31*12/COUNT(B31:M31)) -> 0 | P31: Accountant fees, lawyer consultations, NDA reviews
A32: Office / utilities (home office allocation) | N32: =SUM(B32:M32) -> 0 | O32: =IF(COUNT(B32:M32)=0,0,N32*12/COUNT(B32:M32)) -> 0 | P32: Home office % of rent, internet, phone, electric
A33: Bank fees / Stripe processing | N33: =SUM(B33:M33) -> 0 | O33: =IF(COUNT(B33:M33)=0,0,N33*12/COUNT(B33:M33)) -> 0 | P33: Stripe takes 2.9% + 30¢ per transaction. Add up monthly.
A34: Other operating expenses | N34: =SUM(B34:M34) -> 0 | O34: =IF(COUNT(B34:M34)=0,0,N34*12/COUNT(B34:M34)) -> 0 | P34: Anything else. Itemize in notes.
A35: TOTAL OPERATING EXPENSES | B35: =SUM(B25:B34) -> 123 | C35: =SUM(C25:C34) -> 123 | D35: =SUM(D25:D34) -> 123 | E35: =SUM(E25:E34) -> 123 | F35: =SUM(F25:F34) -> 123 | G35: =SUM(G25:G34) -> 123 | H35: =SUM(H25:H34) -> 123 | I35: =SUM(I25:I34) -> 123 | ... M35: =SUM(M25:M34) -> 123 | N35: =SUM(B35:M35) -> 1476 | O35: =IF(COUNT(B34:M34)=0,0,N35*12/COUNT(B34:M34)) -> 0
A37: NET INCOME | B37: =B21-B35 -> -123 | C37: =C21-C35 -> -123 | D37: =D21-D35 -> -123 | E37: =E21-E35 -> -123 | F37: =F21-F35 -> -23 | G37: =G21-G35 -> -123 | H37: =H21-H35 -> -123 | I37: =I21-I35 -> -123 | ... M37: =M21-M35 -> -123 | N37: =SUM(B37:M37) -> -1376 | O37: =IF(COUNT(B36:M36)=0,0,N37*12/COUNT(B36:M36)) -> 0
A38: Net margin | B38: =IFERROR(B37/B12,0) -> 0 | C38: =IFERROR(C37/C12,0) -> 0 | D38: =IFERROR(D37/D12,0) -> 0 | E38: =IFERROR(E37/E12,0) -> 0 | F38: =IFERROR(F37/F12,0) -> -0.23 | G38: =IFERROR(G37/G12,0) -> 0 | H38: =IFERROR(H37/H12,0) -> 0 | I38: =IFERROR(I37/I12,0) -> 0 | ... N38: =IFERROR(N37/N12,0) -> -13.76
A40: Running YTD net income | B40: =B37 -> -123 | C40: =B40+C37 -> -246 | D40: =C40+D37 -> -369 | E40: =D40+E37 -> -492 | F40: =E40+F37 -> -515 | G40: =F40+G37 -> -638 | H40: =G40+H37 -> -761 | I40: =H40+I37 -> -884 | J40: =I40+J37 -> -1007 | ... M40: =L40+M37 -> -1376 | N40: =M40 -> -1376 | O40: =O37 -> 0

Sheet Clients
A1: Client Roster
A2: Add a row for each client. Status = "active" / "trial" / "churned" / "lead".
A4: Client Name | B4: Tier | C4: MRR ($) | D4: Setup Paid ($) | E4: Start Date | F4: Status | G4: Notes
A5: NorthCove Builders | B5: Starter | C5: 100 | D5: 0 | E5: 2026-04-01 | F5: active | G5: First client. Friend pricing. Invoice not yet collected as of May 2026.
A6: Square K Vacations | B6: TBD | C6: 0 | D6: 0 | E6: 2026-05-01 | F6: trial | G6: Site built, not yet billed. Decide tier + start billing.
A7: WrenchTime Cycles | B7: TBD | C7: 0 | D7: 0 | F7: trial | G7: Site built, not yet billed. Service-shop with external DB. Premium candidate.
A8: Jewelry business | B8: Essential (one-time) | C8: 0 | D8: 0 | F8: lead | G8: Verbal commit $600 one-time. Invoice this week.
A11: Total MRR (active clients): | C11: =SUMIF(F5:F100,"active",C5:C100) -> 100
A12: Annualized MRR: | C12: =C11*12 -> 1200
A13: Active client count: | C13: =COUNTIF(F5:F100,"active") -> 1

Sheet Annual Summary
A1: NGFsystems — Annual Summary
A2: Year-by-year roll-up. Add a new column for each year going forward.
A4: Metric | B4: 2026 (Current) | C4: 2027 | D4: 2028 | E4: 2029 | F4: 2030
A5: Total Income | B5: ='2026 P&L'!N12 -> 100
A6: Total COGS | B6: ='2026 P&L'!N19 -> 0
A7: Gross Profit | B7: ='2026 P&L'!N21 -> 100
A8: Gross Margin % | B8: =IFERROR('2026 P&L'!N21/'2026 P&L'!N12,0) -> 1
A9: Total Operating Expenses | B9: ='2026 P&L'!N35 -> 1476
A10: NET INCOME | B10: ='2026 P&L'!N37 -> -1376
A11: Net Margin % | B11: =IFERROR('2026 P&L'!N37/'2026 P&L'!N12,0) -> -13.76
A12: Active Clients (year-end) | B12: =Clients!C13 -> 1
A13: Annualized MRR (year-end) | B13: =Clients!C12 -> 1200
A16: Year-end checklist
A17: • Confirm every month is filled in on the 2026 P&L sheet
A18: • Save a frozen copy: NGFsystems-PL-2026-Final.xlsx
A19: • Update this Annual Summary by typing the YTD numbers into the 2026 column (so they don't drift if you edit the P&L later)
A20: • Send Annual Summary to accountant for tax filing
A21: • Compare YoY metrics. If revenue grew but net margin shrunk, costs are scaling faster than revenue — investigate.
A22: • Open new workbook for next year and continue tracking.
